abirami_hide_code-4.0.5.data/data/share/jupyter/labextensions/abirami_hide_code/build_log.json
abirami_hide_code-4.0.5.data/data/share/jupyter/labextensions/abirami_hide_code/install.json
abirami_hide_code-4.0.5.data/data/share/jupyter/labextensions/abirami_hide_code/package.json
abirami_hide_code-4.0.5.data/data/share/jupyter/labextensions/abirami_hide_code/static/lib_index_js.517fefc6dbbe2c7dbe14.js
abirami_hide_code-4.0.5.data/data/share/jupyter/labextensions/abirami_hide_code/static/lib_index_js.517fefc6dbbe2c7dbe14.js.map
abirami_hide_code-4.0.5.data/data/share/jupyter/labextensions/abirami_hide_code/static/remoteEntry.249f6054560637083c6f.js
abirami_hide_code-4.0.5.data/data/share/jupyter/labextensions/abirami_hide_code/static/remoteEntry.249f6054560637083c6f.js.map
abirami_hide_code-4.0.5.data/data/share/jupyter/labextensions/abirami_hide_code/static/style.js
abirami_hide_code-4.0.5.data/data/share/jupyter/labextensions/abirami_hide_code/static/style_index_js.a19fb70a273b26a19b21.js
abirami_hide_code-4.0.5.data/data/share/jupyter/labextensions/abirami_hide_code/static/style_index_js.a19fb70a273b26a19b21.js.map
jupyterlab_hide_code/__init__.py
jupyterlab_hide_code/_version.py
abirami_hide_code-4.0.5.dist-info/LICENSE
abirami_hide_code-4.0.5.dist-info/METADATA
abirami_hide_code-4.0.5.dist-info/WHEEL
abirami_hide_code-4.0.5.dist-info/top_level.txt
abirami_hide_code-4.0.5.dist-info/RECORD
